rr/__init__.py
rr/report.py
result_reporter-0.2.1.dist-info/METADATA
result_reporter-0.2.1.dist-info/WHEEL
result_reporter-0.2.1.dist-info/RECORD
