Metadata-Version: 2.1
Name: result-reporter
Version: 0.2.1
Summary: A context manager to report results to and endpoint.
License: MIT
Author: Paul Logston
Author-email: paul.logston@gmail.com
Requires-Python: >=3.8
Classifier: License :: OSI Approved :: MIT License
Classifier: Programming Language :: Python :: 3
Classifier: Programming Language :: Python :: 3.8
Classifier: Programming Language :: Python :: 3.9
Classifier: Programming Language :: Python :: 3.10
Classifier: Programming Language :: Python :: 3.11
Requires-Dist: requests (>=2.25.0)
